Workbook

Sheet Project Overview
B2: PROCUREMENT PORTFOLIO — 3 BEDROOM FLAT (GERMAN FLOOR FOUNDATION)
B3: Prepared by: Akintunde Teslim | Project: Residential Building | Location: Lagos, Nigeria | Date: Q1 2025
B6: PROJECT SCOPE & SPECIFICATIONS
B7: Project Title: | C7: Construction of 3-Bedroom Flat with German Floor Foundation
B8: Building Type: | C8: Residential Duplex — Ground Floor + 1st Floor (3 Bedrooms, 2 Sitting Rooms, Kitchen, 3 Bathrooms)
B9: Foundation Type: | C9: German Floor (Raft/Mat Foundation) — Suitable for Lagos soft/sandy soil conditions
B10: Plot Size: | C10: 600 sqm | Building Footprint: ~180 sqm | Total Floor Area: ~360 sqm (2 floors)
B11: Construction Duration: | C11: Estimated 18 months (Phase 1: Foundation + DPC = 3 months; Superstructure = 9 months; Finishing = 6 months)
B12: Procurement Officer: | C12: Akintunde Teslim | Designation: Senior Procurement Officer
B13: Project Sponsor: | C13: Private Developer | Budget Approval: Confirmed
B14: Delivery Strategy: | C14: Direct procurement + competitive tendering for major items; frame agreements with key suppliers
B16: PROJECT BUDGET SUMMARY
B17: MATERIALS BUDGET | D17: LABOUR COST | F17: PROFESSIONAL FEES | H17: CONTINGENCY (10%)
B18: ='Bill of Quantities'!L4 -> 63574700 | D18: ='Labour Cost'!G4 -> 0 | F18: ='Professional Fees'!E4 -> 0 | H18: =('Bill of Quantities'!L4+'Labour Cost'!G4+'Professional Fees'!E4)*0.1 -> 6357470
B19: ₦ | D19: ₦ | F19: ₦ | H19: ₦
B20: GRAND TOTAL PROJECT COST (incl. Contingency) | H20: ='Bill of Quantities'!L4+'Labour Cost'!G4+'Professional Fees'!E4+('Bill of Quantities'!L4+'Labour Cost'!G4+'Professional Fees'!E4)*0.1 -> 69932170
B22: PROCUREMENT & CONSTRUCTION PHASE PLAN
B23: Phase | C23: Description | D23: Duration | E23: Key Materials/Activities | G23: Procurement Method | H23: Status
B24: Phase 1 | C24: Site Preparation & Foundation (German Floor) | D24: Month 1-3 | E24: Excavation, Blinding concrete, BRC mesh, Foundation concrete, DPC, Backfill | G24: Open Competitive Tendering | H24: IN PROGRESS
B25: Phase 2 | C25: Ground Floor Superstructure | D25: Month 4-8 | E25: Block work, Columns, Beams, Lintel, Ring beam, Ground floor slab | G25: Framework Agreement | H25: UPCOMING
B26: Phase 3 | C26: First Floor Superstructure | D26: Month 5-10 | E26: Block work, Columns, Beams, Roof beam, Roof truss & covering | G26: Framework Agreement | H26: UPCOMING
B27: Phase 4 | C27: Roofing & External Works | D27: Month 9-12 | E27: Roof truss, Aluminum roofing, Fascia, Rain gutters, External rendering | G27: Direct Procurement | H27: UPCOMING
B28: Phase 5 | C28: Mechanical, Electrical & Plumbing | D28: Month 11-15 | E28: Plumbing, Electrical wiring, AC points, Solar system, Water tank | G28: Specialist Contractors | H28: UPCOMING
B29: Phase 6 | C29: Internal & External Finishing | D29: Month 13-18 | E29: Floor tiles, Wall tiles, Painting, Doors, Windows, Fittings, Landscaping | G29: Direct + Competitive | H29: UPCOMING

Sheet Bill of Quantities
B1: BILL OF QUANTITIES — MATERIALS PROCUREMENT
B2: 3-Bedroom Flat | German Floor Foundation | Lagos, Nigeria | All costs in Nigerian Naira (₦)
B4: TOTAL MATERIALS COST | L4: =L175 -> 63574700
B6: # | C6: Description | D6: Unit | E6: Qty | F6: Unit Rate (₦) | G6: Amount (₦) | H6: Vendor 1 Quote (₦) | I6: Vendor 2 Quote (₦) | J6: Vendor 3 Quote (₦) | K6: Selected Vendor | L6: Savings (₦)
B7: A. SITE PREPARATION & EXCAVATION
B8: A1 | C8: Site clearing and levelling (600 sqm) | D8: sqm | E8: 600 | F8: 450 | G8: =E8*F8 -> 270000 | H8: 270000 | I8: 280000 | J8: 265000 | K8: Suntech Nig. Ltd | L8: =MAX(H8,I8,J8)-G8 -> 10000
B9: A2 | C9: Excavation for German floor foundation (180 sqm × 0.6m deep) | D9: m³ | E9: 108 | F9: 3500 | G9: =E9*F9 -> 378000 | H9: 380000 | I9: 405000 | J9: 370000 | K9: Kola Excavators | L9: =MAX(H9,I9,J9)-G9 -> 27000
B10: A3 | C10: Anti-termite soil treatment | D10: sqm | E10: 180 | F10: 1200 | G10: =E10*F10 -> 216000 | H10: 218000 | I10: 225000 | J10: 215000 | K10: Termiguard Nig. | L10: =MAX(H10,I10,J10)-G10 -> 9000
B11: A4 | C11: Hardcore filling and compaction (150mm) | D11: m³ | E11: 27 | F11: 8500 | G11: =E11*F11 -> 229500 | H11: 232000 | I11: 240000 | J11: 228000 | K11: Suntech Nig. Ltd | L11: =MAX(H11,I11,J11)-G11 -> 10500
B12: A5 | C12: Blinding concrete (50mm, 1:3:6 mix, 180 sqm) | D12: m³ | E12: 9 | F12: 55000 | G12: =E12*F12 -> 495000 | H12: 500000 | I12: 510000 | J12: 495000 | K12: Readymix Concrete Ng | L12: =MAX(H12,I12,J12)-G12 -> 15000
B13: SUBTOTAL A | G13: =SUM(G8:G12) -> 1588500 | L13: =SUM(L8:L12) -> 71500
B15: B. GERMAN FLOOR FOUNDATION CONCRETE WORKS
B16: B1 | C16: BRC mesh (A393) — German floor reinforcement (180 sqm) | D16: sheets | E16: 30 | F16: 85000 | G16: =E16*F16 -> 2550000 | H16: 2580000 | I16: 2600000 | J16: 2550000 | K16: Steel Baron Nig. | L16: =MAX(H16,I16,J16)-G16 -> 50000
B17: B2 | C17: Mild steel rod Y16 (foundation column starters) | D17: tonnes | E17: 0.8 | F17: 650000 | G17: =E17*F17 -> 520000 | H17: 525000 | I17: 530000 | J17: 520000 | K17: Dangote Steel | L17: =MAX(H17,I17,J17)-G17 -> 10000
B18: B3 | C18: Mild steel rod Y12 (ring beam & tie bars) | D18: tonnes | E18: 0.5 | F18: 650000 | G18: =E18*F18 -> 325000 | H18: 328000 | I18: 330000 | J18: 325000 | K18: Dangote Steel | L18: =MAX(H18,I18,J18)-G18 -> 5000
B19: B4 | C19: Ready mix concrete 25N/mm² — Raft slab (180 sqm × 250mm) | D19: m³ | E19: 47 | F19: 55000 | G19: =E19*F19 -> 2585000 | H19: 2600000 | I19: 2650000 | J19: 2580000 | K19: Lafarge ReadyMix | L19: =MAX(H19,I19,J19)-G19 -> 65000
B20: B5 | C20: Binding wire (1kg rolls) | D20: rolls | E20: 25 | F20: 2800 | G20: =E20*F20 -> 70000 | H20: 71000 | I20: 72000 | J20: 70000 | K20: Local market | L20: =MAX(H20,I20,J20)-G20 -> 2000
B21: B6 | C21: Form work for ground beam edges (50mm boards) | D21: sqm | E21: 45 | F21: 4500 | G21: =E21*F21 -> 202500 | H21: 205000 | I21: 208000 | J21: 202000 | K21: Timber King Abk | L21: =MAX(H21,I21,J21)-G21 -> 5500
B22: B7 | C22: Damp proof membrane (DPM) 1200 gauge polythene | D22: rolls | E22: 12 | F22: 18000 | G22: =E22*F22 -> 216000 | H22: 217000 | I22: 220000 | J22: 215000 | K22: BuildPro Supplies | L22: =MAX(H22,I22,J22)-G22 -> 4000
B23: B8 | C23: Sand filling to floor level (after DPC) | D23: m³ | E23: 54 | F23: 6500 | G23: =E23*F23 -> 351000 | H23: 354000 | I23: 360000 | J23: 350000 | K23: Kola Excavators | L23: =MAX(H23,I23,J23)-G23 -> 9000
B24: B9 | C24: Damp proof course (DPC) bricks — ground level | D24: sqm | E24: 75 | F24: 3500 | G24: =E24*F24 -> 262500 | H24: 264000 | I24: 268000 | J24: 260000 | K24: Premier Blocks Ltd | L24: =MAX(H24,I24,J24)-G24 -> 5500
B25: SUBTOTAL B | G25: =SUM(G16:G24) -> 7082000 | L25: =SUM(L16:L24) -> 156000
B27: C. BLOCK WORK & SUPERSTRUCTURE
B28: C1 | C28: 9-inch hollow blocks (6-inch equivalent for foundation) | D28: blocks | E28: 4200 | F28: 380 | G28: =E28*F28 -> 1596000 | H28: 1600000 | I28: 1620000 | J28: 1590000 | K28: Premier Blocks Ltd | L28: =MAX(H28,I28,J28)-G28 -> 24000
B29: C2 | C29: 6-inch solid blocks (superstructure ground floor) | D29: blocks | E29: 3500 | F29: 320 | G29: =E29*F29 -> 1120000 | H29: 1125000 | I29: 1130000 | J29: 1120000 | K29: Premier Blocks Ltd | L29: =MAX(H29,I29,J29)-G29 -> 10000
B30: C3 | C30: 6-inch hollow blocks (superstructure 1st floor) | D30: blocks | E30: 2800 | F30: 310 | G30: =E30*F30 -> 868000 | H30: 870000 | I30: 875000 | J30: 865000 | K30: Premier Blocks Ltd | L30: =MAX(H30,I30,J30)-G30 -> 7000
B31: C4 | C31: Portland cement — Dangote 42.5 (bags) | D31: bags | E31: 650 | F31: 7200 | G31: =E31*F31 -> 4680000 | H31: 4700000 | I31: 4750000 | J31: 4680000 | K31: Dangote Cement Dist. | L31: =MAX(H31,I31,J31)-G31 -> 70000
B32: C5 | C32: Sharp sand (tipper loads — 5 tonnes each) | D32: loads | E32: 35 | F32: 45000 | G32: =E32*F32 -> 1575000 | H32: 1580000 | I32: 1600000 | J32: 1570000 | K32: Lagos Sand Dealers | L32: =MAX(H32,I32,J32)-G32 -> 25000
B33: C6 | C33: Granite 3/4 (coarse aggregate — tipper loads) | D33: loads | E33: 20 | F33: 55000 | G33: =E33*F33 -> 1100000 | H33: 1105000 | I33: 1110000 | J33: 1100000 | K33: Apapa Quarry Ltd | L33: =MAX(H33,I33,J33)-G33 -> 10000
B34: C7 | C34: Steel rod Y16 (columns and beams) | D34: tonnes | E34: 3.5 | F34: 650000 | G34: =E34*F34 -> 2275000 | H34: 2285000 | I34: 2290000 | J34: 2275000 | K34: Dangote Steel | L34: =MAX(H34,I34,J34)-G34 -> 15000
B35: C8 | C35: Steel rod Y12 (secondary reinforcement) | D35: tonnes | E35: 2 | F35: 650000 | G35: =E35*F35 -> 1300000 | H35: 1305000 | I35: 1310000 | J35: 1300000 | K35: Dangote Steel | L35: =MAX(H35,I35,J35)-G35 -> 10000
B36: C9 | C36: Steel rod Y10 (stirrups and links) | D36: tonnes | E36: 1 | F36: 650000 | G36: =E36*F36 -> 650000 | H36: 653000 | I36: 658000 | J36: 648000 | K36: Dangote Steel | L36: =MAX(H36,I36,J36)-G36 -> 8000
B37: C10 | C37: Steel rod Y8 (distribution bars, lintels) | D37: tonnes | E37: 0.8 | F37: 650000 | G37: =E37*F37 -> 520000 | H37: 523000 | I37: 526000 | J37: 520000 | K37: Dangote Steel | L37: =MAX(H37,I37,J37)-G37 -> 6000
B38: C11 | C38: Binding wire (coils) | D38: coils | E38: 50 | F38: 2800 | G38: =E38*F38 -> 140000 | H38: 141000 | I38: 143000 | J38: 140000 | K38: Local market | L38: =MAX(H38,I38,J38)-G38 -> 3000
B39: C12 | C39: Form work timber (2×3 and 2×6 boards) | D39: pieces | E39: 200 | F39: 3500 | G39: =E39*F39 -> 700000 | H39: 703000 | I39: 708000 | J39: 698000 | K39: Timber King Abk | L39: =MAX(H39,I39,J39)-G39 -> 8000
... B45: C18 | C45: Window/door props (acrow / adjustable props) | D45: pieces | E45: 30 | F45: 12000 | G45: =E45*F45 -> 360000 | H45: 361000 | I45: 365000 | J45: 358000 | K45: BuildPro Supplies | L45: =MAX(H45,I45,J45)-G45 -> 5000
B46: SUBTOTAL C | G46: =SUM(G28:G45) -> 21179000 | L46: =SUM(L28:L45) -> 246000
B48: D. ROOFING WORKS
B49: D1 | C49: Roofing timber (2×6 rafters) | D49: pieces | E49: 100 | F49: 3500 | G49: =E49*F49 -> 350000 | H49: 350000 | I49: 355000 | J49: 345000 | K49: Timber King Abk | L49: =MAX(H49,I49,J49)-G49 -> 5000
B50: D2 | C50: Roofing timber (2×3 purlins) | D50: pieces | E50: 200 | F50: 2200 | G50: =E50*F50 -> 440000 | H50: 443000 | I50: 448000 | J50: 440000 | K50: Timber King Abk | L50: =MAX(H50,I50,J50)-G50 -> 8000
B51: D3 | C51: Aluminum long span roofing sheets (0.55mm) | D51: sqm | E51: 280 | F51: 3800 | G51: =E51*F51 -> 1064000 | H51: 1065000 | I51: 1070000 | J51: 1060000 | K51: Alum Roofing Ng | L51: =MAX(H51,I51,J51)-G51 -> 6000
B52: D4 | C52: Ridge cap aluminum | D52: length | E52: 25 | F52: 4500 | G52: =E52*F52 -> 112500 | H52: 113000 | I52: 115000 | J52: 111000 | K52: Alum Roofing Ng | L52: =MAX(H52,I52,J52)-G52 -> 2500
B53: D5 | C53: Fascia board aluminum | D53: length | E53: 60 | F53: 3200 | G53: =E53*F53 -> 192000 | H53: 193000 | I53: 195000 | J53: 191000 | K53: Alum Roofing Ng | L53: =MAX(H53,I53,J53)-G53 -> 3000
B54: D6 | C54: Rain gutters (PVC 100mm half-round) | D54: length | E54: 50 | F54: 4200 | G54: =E54*F54 -> 210000 | H54: 211000 | I54: 213000 | J54: 209000 | K54: RoofPro Nig. | L54: =MAX(H54,I54,J54)-G54 -> 3000
B55: D7 | C55: Downpipes PVC 75mm | D55: length | E55: 24 | F55: 3500 | G55: =E55*F55 -> 84000 | H55: 85000 | I55: 87000 | J55: 83000 | K55: RoofPro Nig. | L55: =MAX(H55,I55,J55)-G55 -> 3000
B56: D8 | C56: Roofing nails / screws (assorted) | D56: kg | E56: 30 | F56: 1500 | G56: =E56*F56 -> 45000 | H56: 46000 | I56: 47000 | J56: 45000 | K56: Local market | L56: =MAX(H56,I56,J56)-G56 -> 2000
B57: D9 | C57: Roof insulation board (50mm) | D57: sqm | E57: 280 | F57: 2800 | G57: =E57*F57 -> 784000 | H57: 786000 | I57: 790000 | J57: 782000 | K57: BuildPro Supplies | L57: =MAX(H57,I57,J57)-G57 -> 6000
B58: D10 | C58: Roof overhang soffit board (cement board) | D58: sqm | E58: 60 | F58: 3500 | G58: =E58*F58 -> 210000 | H58: 211000 | I58: 213000 | J58: 209000 | K58: BuildPro Supplies | L58: =MAX(H58,I58,J58)-G58 -> 3000
B59: SUBTOTAL D | G59: =SUM(G49:G58) -> 3491500 | L59: =SUM(L49:L58) -> 41500
B61: E. WINDOWS, DOORS & IRONMONGERY
B62: E1 | C62: Aluminium sliding windows 1200×1200mm | D62: units | E62: 12 | F62: 85000 | G62: =E62*F62 -> 1020000 | H62: 1022000 | I62: 1025000 | J62: 1018000 | K62: Alumaco Nig. Ltd | L62: =MAX(H62,I62,J62)-G62 -> 5000
B63: E2 | C63: Aluminium casement windows 600×900mm | D63: units | E63: 8 | F63: 65000 | G63: =E63*F63 -> 520000 | H63: 522000 | I63: 525000 | J63: 519000 | K63: Alumaco Nig. Ltd | L63: =MAX(H63,I63,J63)-G63 -> 5000
B64: E3 | C64: External security door (steel) — main entrance | D64: units | E64: 1 | F64: 380000 | G64: =E64*F64 -> 380000 | H64: 382000 | I64: 385000 | J64: 378000 | K64: Ironmax Nig. | L64: =MAX(H64,I64,J64)-G64 -> 5000
B65: E4 | C65: External security door (steel) — back entrance | D65: units | E65: 1 | F65: 280000 | G65: =E65*F65 -> 280000 | H65: 282000 | I65: 285000 | J65: 278000 | K65: Ironmax Nig. | L65: =MAX(H65,I65,J65)-G65 -> 5000
B66: E5 | C66: Internal flush doors (solid core, 900×2100mm) | D66: units | E66: 9 | F66: 65000 | G66: =E66*F66 -> 585000 | H66: 587000 | I66: 590000 | J66: 583000 | K66: Woodcraft Nig. | L66: =MAX(H66,I66,J66)-G66 -> 5000
B67: E6 | C67: Internal flush doors (bathroom, 700×2100mm) | D67: units | E67: 3 | F67: 55000 | G67: =E67*F67 -> 165000 | H67: 166000 | I67: 168000 | J67: 164000 | K67: Woodcraft Nig. | L67: =MAX(H67,I67,J67)-G67 -> 3000
B68: E7 | C68: Door frames (hardwood) | D68: units | E68: 14 | F68: 18000 | G68: =E68*F68 -> 252000 | H68: 253000 | I68: 255000 | J68: 251000 | K68: Woodcraft Nig. | L68: =MAX(H68,I68,J68)-G68 -> 3000
B69: E8 | C69: Door handles, hinges, bolts (complete sets) | D69: sets | E69: 14 | F69: 8500 | G69: =E69*F69 -> 119000 | H69: 120000 | I69: 122000 | J69: 118000 | K69: Ironmax Nig. | L69: =MAX(H69,I69,J69)-G69 -> 3000
B70: E9 | C70: Window burglar proof (black iron 16mm rods) | D70: sqm | E70: 60 | F70: 12000 | G70: =E70*F70 -> 720000 | H70: 722000 | I70: 725000 | J70: 719000 | K70: Ironmax Nig. | L70: =MAX(H70,I70,J70)-G70 -> 5000
B71: E10 | C71: Window nets / insect screens (aluminium frame) | D71: units | E71: 20 | F71: 18000 | G71: =E71*F71 -> 360000 | H71: 362000 | I71: 365000 | J71: 358000 | K71: Alumaco Nig. Ltd | L71: =MAX(H71,I71,J71)-G71 -> 5000
B72: SUBTOTAL E | G72: =SUM(G62:G71) -> 4401000 | L72: =SUM(L62:L71) -> 44000
B74: F. PLUMBING & WATER SUPPLY
B75: F1 | C75: uPVC pipes 110mm (drainage/sewer) | D75: length | E75: 80 | F75: 4200 | G75: =E75*F75 -> 336000 | H75: 337000 | I75: 340000 | J75: 334000 | K75: Vanguard Pipes | L75: =MAX(H75,I75,J75)-G75 -> 4000
B76: F2 | C76: uPVC pipes 75mm (drainage) | D76: length | E76: 60 | F76: 3200 | G76: =E76*F76 -> 192000 | H76: 193000 | I76: 195000 | J76: 191000 | K76: Vanguard Pipes | L76: =MAX(H76,I76,J76)-G76 -> 3000
B77: F3 | C77: PPR hot/cold water pipes 25mm | D77: length | E77: 120 | F77: 1800 | G77: =E77*F77 -> 216000 | H77: 217000 | I77: 219000 | J77: 215000 | K77: Vanguard Pipes | L77: =MAX(H77,I77,J77)-G77 -> 3000
B78: F4 | C78: PPR pipes 20mm (branch connections) | D78: length | E78: 80 | F78: 1400 | G78: =E78*F78 -> 112000 | H78: 113000 | I78: 115000 | J78: 111000 | K78: Vanguard Pipes | L78: =MAX(H78,I78,J78)-G78 -> 3000
B79: F5 | C79: Overhead water tank 5000L (polyethylene) | D79: units | E79: 1 | F79: 185000 | G79: =E79*F79 -> 185000 | H79: 186000 | I79: 188000 | J79: 183000 | K79: Roto Tanks Nig. | L79: =MAX(H79,I79,J79)-G79 -> 3000
B80: F6 | C80: Underground storage tank 10000L | D80: units | E80: 1 | F80: 420000 | G80: =E80*F80 -> 420000 | H80: 422000 | I80: 425000 | J80: 418000 | K80: Roto Tanks Nig. | L80: =MAX(H80,I80,J80)-G80 -> 5000
B81: F7 | C81: Water pump (0.5HP submersible + surface) | D81: units | E81: 2 | F81: 85000 | G81: =E81*F81 -> 170000 | H81: 172000 | I81: 174000 | J81: 170000 | K81: Mikano Pumps | L81: =MAX(H81,I81,J81)-G81 -> 4000
B82: F8 | C82: Water closet (WC) complete set — standard | D82: units | E82: 3 | F82: 95000 | G82: =E82*F82 -> 285000 | H82: 287000 | I82: 290000 | J82: 283000 | K82: Sanitech Nig. | L82: =MAX(H82,I82,J82)-G82 -> 5000
B83: F9 | C83: Pedestal wash hand basin complete | D83: units | E83: 3 | F83: 65000 | G83: =E83*F83 -> 195000 | H83: 197000 | I83: 199000 | J83: 194000 | K83: Sanitech Nig. | L83: =MAX(H83,I83,J83)-G83 -> 4000
B84: F10 | C84: Kitchen sink (stainless steel, double bowl) | D84: units | E84: 1 | F84: 78000 | G84: =E84*F84 -> 78000 | H84: 79000 | I84: 81000 | J84: 77000 | K84: Sanitech Nig. | L84: =MAX(H84,I84,J84)-G84 -> 3000
B85: F11 | C85: Shower set — rainfall type (chrome) | D85: units | E85: 3 | F85: 45000 | G85: =E85*F85 -> 135000 | H85: 136000 | I85: 138000 | J85: 133000 | K85: Sanitech Nig. | L85: =MAX(H85,I85,J85)-G85 -> 3000
B86: F12 | C86: Gate valve and stop cock (various sizes) | D86: units | E86: 20 | F86: 5500 | G86: =E86*F86 -> 110000 | H86: 111000 | I86: 113000 | J86: 109000 | K86: Vanguard Pipes | L86: =MAX(H86,I86,J86)-G86 -> 3000
B87: F13 | C87: Septic tank construction (manhole + soakaway rings) | D87: sum | E87: 1 | F87: 280000 | G87: =E87*F87 -> 280000 | H87: 282000 | I87: 285000 | J87: 278000 | K87: Civil Works Nig. | L87: =MAX(H87,I87,J87)-G87 -> 5000
B88: SUBTOTAL F | G88: =SUM(G75:G87) -> 2714000 | L88: =SUM(L75:L87) -> 48000
B90: G. ELECTRICAL INSTALLATION
B91: G1 | C91: 2.5mm twin & earth cables (100m drums) | D91: drums | E91: 8 | F91: 58000 | G91: =E91*F91 -> 464000 | H91: 466000 | I91: 470000 | J91: 462000 | K91: Nigerchin Cables | L91: =MAX(H91,I91,J91)-G91 -> 6000
B92: G2 | C92: 4mm twin & earth cables (100m drums) | D92: drums | E92: 4 | F92: 95000 | G92: =E92*F92 -> 380000 | H92: 382000 | I92: 385000 | J92: 378000 | K92: Nigerchin Cables | L92: =MAX(H92,I92,J92)-G92 -> 5000
B93: G3 | C93: 6mm single core cables (100m drums) | D93: drums | E93: 2 | F93: 120000 | G93: =E93*F93 -> 240000 | H93: 242000 | I93: 244000 | J93: 240000 | K93: Nigerchin Cables | L93: =MAX(H93,I93,J93)-G93 -> 4000
B94: G4 | C94: Conduit pipes 20mm (electrical) | D94: length | E94: 200 | F94: 1200 | G94: =E94*F94 -> 240000 | H94: 242000 | I94: 244000 | J94: 240000 | K94: Nigerchin Cables | L94: =MAX(H94,I94,J94)-G94 -> 4000
B95: G5 | C95: Consumer unit / distribution board (12-way) | D95: units | E95: 2 | F95: 45000 | G95: =E95*F95 -> 90000 | H95: 91000 | I95: 93000 | J95: 89000 | K95: Clipsal Nigeria | L95: =MAX(H95,I95,J95)-G95 -> 3000
B96: G6 | C96: MCB single pole 16A (circuit breakers) | D96: units | E96: 24 | F96: 2800 | G96: =E96*F96 -> 67200 | H96: 68000 | I96: 69000 | J96: 67000 | K96: Schneider Elec. | L96: =MAX(H96,I96,J96)-G96 -> 1800
B97: G7 | C97: Single socket outlets (surface/flush) | D97: units | E97: 40 | F97: 3500 | G97: =E97*F97 -> 140000 | H97: 141000 | I97: 143000 | J97: 139000 | K97: Clipsal Nigeria | L97: =MAX(H97,I97,J97)-G97 -> 3000
B98: G8 | C98: Double socket outlets | D98: units | E98: 20 | F98: 4500 | G98: =E98*F98 -> 90000 | H98: 91000 | I98: 93000 | J98: 89000 | K98: Clipsal Nigeria | L98: =MAX(H98,I98,J98)-G98 -> 3000
B99: G9 | C99: Switch plates (1-gang, 2-gang) | D99: units | E99: 30 | F99: 2800 | G99: =E99*F99 -> 84000 | H99: 85000 | I99: 87000 | J99: 83000 | K99: Clipsal Nigeria | L99: =MAX(H99,I99,J99)-G99 -> 3000
B100: G10 | C100: Light fittings — LED downlights 12W | D100: units | E100: 30 | F100: 8500 | G100: =E100*F100 -> 255000 | H100: 256000 | I100: 258000 | J100: 253000 | K100: Philips Nigeria | L100: =MAX(H100,I100,J100)-G100 -> 3000
B101: G11 | C101: Exterior wall lights (weatherproof) | D101: units | E101: 8 | F101: 12000 | G101: =E101*F101 -> 96000 | H101: 97000 | I101: 99000 | J101: 95000 | K101: Philips Nigeria | L101: =MAX(H101,I101,J101)-G101 -> 3000
B102: G12 | C102: Inverter + 200Ah batteries (2-unit solar system) | D102: sets | E102: 1 | F102: 750000 | G102: =E102*F102 -> 750000 | H102: 752000 | I102: 756000 | J102: 748000 | K102: Victron Energy Ng | L102: =MAX(H102,I102,J102)-G102 -> 6000
... B105: G15 | C105: Prepaid meter + armoured cable (EKEDC connection) | D105: sum | E105: 1 | F105: 125000 | G105: =E105*F105 -> 125000 | H105: 126000 | I105: 128000 | J105: 123000 | K105: EKEDC Approved | L105: =MAX(H105,I105,J105)-G105 -> 3000
B106: SUBTOTAL G | G106: =SUM(G91:G105) -> 3796200 | L106: =SUM(L91:L105) -> 56800
B108: H. WALL PLASTERING & SCREEDING
B109: H1 | C109: Internal plastering (walls — 15mm coat) | D109: sqm | E109: 760 | F109: 1800 | G109: =E109*F109 -> 1368000 | H109: 1370000 | I109: 1375000 | J109: 1365000 | K109: Buildmat Nig. | L109: =MAX(H109,I109,J109)-G109 -> 7000
B110: H2 | C110: External rendering (20mm, textured finish) | D110: sqm | E110: 420 | F110: 2200 | G110: =E110*F110 -> 924000 | H110: 926000 | I110: 930000 | J110: 922000 | K110: Buildmat Nig. | L110: =MAX(H110,I110,J110)-G110 -> 6000
B111: H3 | C111: Floor screeding (ground floor 50mm) | D111: sqm | E111: 180 | F111: 1500 | G111: =E111*F111 -> 270000 | H111: 271000 | I111: 273000 | J111: 269000 | K111: Buildmat Nig. | L111: =MAX(H111,I111,J111)-G111 -> 3000
B112: H4 | C112: Floor screeding (first floor 50mm) | D112: sqm | E112: 180 | F112: 1500 | G112: =E112*F112 -> 270000 | H112: 271000 | I112: 273000 | J112: 269000 | K112: Buildmat Nig. | L112: =MAX(H112,I112,J112)-G112 -> 3000
B113: H5 | C113: Ceiling board (9mm POP / gyp board) | D113: sqm | E113: 360 | F113: 3500 | G113: =E113*F113 -> 1260000 | H113: 1263000 | I113: 1268000 | J113: 1258000 | K113: CeilPro Nig. | L113: =MAX(H113,I113,J113)-G113 -> 8000
B114: H6 | C114: Ceiling cornice & moulding | D114: length | E114: 200 | F114: 1800 | G114: =E114*F114 -> 360000 | H114: 362000 | I114: 365000 | J114: 358000 | K114: CeilPro Nig. | L114: =MAX(H114,I114,J114)-G114 -> 5000
B115: H7 | C115: Cement & sand (plastering work) | D115: bags | E115: 180 | F115: 7200 | G115: =E115*F115 -> 1296000 | H115: 1298000 | I115: 1305000 | J115: 1292000 | K115: Dangote Cement | L115: =MAX(H115,I115,J115)-G115 -> 9000
B116: SUBTOTAL H | G116: =SUM(G109:G115) -> 5748000 | L116: =SUM(L109:L115) -> 41000
...

Sheet Labour Cost
B1: LABOUR COST SCHEDULE — 3 BEDROOM FLAT
B2: All costs in Nigerian Naira (₦) | Based on Lagos State minimum wage rates + market premium
B4: TOTAL LABOUR COST | J4: =J85 -> 49765000
B6: # | C6: Trade / Activity | D6: Phase | E6: Duration | F6: No. of Workers | G6: Daily Rate (₦/worker) | H6: Total Days | I6: Man-Days | J6: Total Labour (₦)
B7: SECTION A — SITE PREPARATION & FOUNDATION
B8: L01 | C8: Site foreman / Supervisor | D8: Phase 1 | E8: 18 months | F8: 1 | G8: 35000 | H8: N/A | I8: 18 | J8: =G8*I8 -> 630000
B9: L02 | C9: Civil/Structural Engineer (site visits) | D9: Phase 1–3 | E9: 18 months | F9: 1 | G9: 150000 | H9: N/A | I9: 18 | J9: =G9*I9 -> 2700000
B10: L03 | C10: Site clearance labourers | D10: Phase 1 | E10: 5 days | F10: 8 | G10: 3500 | H10: 5 | I10: =F10*H10 -> 40 | J10: =I10*G10 -> 140000
B11: L04 | C11: Excavation gang (German floor) | D11: Phase 1 | E11: 10 days | F11: 6 | G11: 4500 | H11: 10 | I11: =F11*H11 -> 60 | J11: =I11*G11 -> 270000
B12: L05 | C12: Anti-termite treatment applicator | D12: Phase 1 | E12: 2 days | F12: 2 | G12: 5000 | H12: 2 | I12: =F12*H12 -> 4 | J12: =I12*G12 -> 20000
B13: L06 | C13: Hardcore laying & compaction labourers | D13: Phase 1 | E13: 5 days | F13: 4 | G13: 3500 | H13: 5 | I13: =F13*H13 -> 20 | J13: =I13*G13 -> 70000
B14: L07 | C14: Blinding concrete gang (mixing & pouring) | D14: Phase 1 | E14: 3 days | F14: 6 | G14: 4000 | H14: 3 | I14: =F14*H14 -> 18 | J14: =I14*G14 -> 72000
B15: L08 | C15: BRC mesh placement & binding workers | D15: Phase 1 | E15: 5 days | F15: 6 | G15: 4500 | H15: 5 | I15: =F15*H15 -> 30 | J15: =I15*G15 -> 135000
B16: L09 | C16: Foundation concrete gang (raft pour) | D16: Phase 1 | E16: 3 days | F16: 10 | G16: 5000 | H16: 3 | I16: =F16*H16 -> 30 | J16: =I16*G16 -> 150000
B17: L10 | C17: DPC bricklaying gang | D17: Phase 1 | E17: 4 days | F17: 6 | G17: 4500 | H17: 4 | I17: =F17*H17 -> 24 | J17: =I17*G17 -> 108000
B18: SUBTOTAL A — FOUNDATION LABOUR | J18: =SUM(J8:J17) -> 4295000
B20: SECTION B — SUPERSTRUCTURE & BLOCK WORK
B21: L11 | C21: Master bricklayer (ground floor) | D21: Phase 2 | E21: 30 days | F21: 4 | G21: 8000 | H21: 30 | I21: =F21*H21 -> 120 | J21: =I21*G21 -> 960000
B22: L12 | C22: Assistant bricklayers (ground floor) | D22: Phase 2 | E22: 30 days | F22: 8 | G22: 4500 | H22: 30 | I22: =F22*H22 -> 240 | J22: =I22*G22 -> 1080000
B23: L13 | C23: Master bricklayer (first floor) | D23: Phase 3 | E23: 30 days | F23: 4 | G23: 8000 | H23: 30 | I23: =F23*H23 -> 120 | J23: =I23*G23 -> 960000
B24: L14 | C24: Assistant bricklayers (first floor) | D24: Phase 3 | E24: 30 days | F24: 8 | G24: 4500 | H24: 30 | I24: =F24*H24 -> 240 | J24: =I24*G24 -> 1080000
B25: L15 | C25: Steel bender / fixer (columns & beams) | D25: Phase 2–3 | E25: 40 days | F25: 4 | G25: 7500 | H25: 40 | I25: =F25*H25 -> 160 | J25: =I25*G25 -> 1200000
B26: L16 | C26: Form work carpenter (shuttering) | D26: Phase 2–3 | E26: 35 days | F26: 4 | G26: 7000 | H26: 35 | I26: =F26*H26 -> 140 | J26: =I26*G26 -> 980000
B27: L17 | C27: Concrete gang (columns, beams, slabs) | D27: Phase 2–3 | E27: 20 days | F27: 8 | G27: 5000 | H27: 20 | I27: =F27*H27 -> 160 | J27: =I27*G27 -> 800000
B28: L18 | C28: Ring beam & lintel gang | D28: Phase 2–3 | E28: 10 days | F28: 6 | G28: 5000 | H28: 10 | I28: =F28*H28 -> 60 | J28: =I28*G28 -> 300000
B29: SUBTOTAL B — SUPERSTRUCTURE LABOUR | J29: =SUM(J21:J28) -> 7360000
B31: SECTION C — ROOFING
B32: L19 | C32: Master carpenter (roof truss) | D32: Phase 4 | E32: 20 days | F32: 2 | G32: 9000 | H32: 20 | I32: =F32*H32 -> 40 | J32: =I32*G32 -> 360000
B33: L20 | C33: Assistant carpenters (roof truss) | D33: Phase 4 | E33: 20 days | F33: 4 | G33: 5000 | H33: 20 | I33: =F33*H33 -> 80 | J33: =I33*G33 -> 400000
B34: L21 | C34: Aluminum roofing fixers | D34: Phase 4 | E34: 10 days | F34: 4 | G34: 7000 | H34: 10 | I34: =F34*H34 -> 40 | J34: =I34*G34 -> 280000
B35: L22 | C35: Fascia, gutter & downpipe fitters | D35: Phase 4 | E35: 5 days | F35: 3 | G35: 5500 | H35: 5 | I35: =F35*H35 -> 15 | J35: =I35*G35 -> 82500
B36: SUBTOTAL C — ROOFING LABOUR | J36: =SUM(J32:J35) -> 1122500
B38: SECTION D — PLUMBING
B39: L23 | C39: Licensed plumber (master) | D39: Phase 5 | E39: 45 days | F39: 1 | G39: 12000 | H39: 45 | I39: =F39*H39 -> 45 | J39: =I39*G39 -> 540000
B40: L24 | C40: Plumbing assistant | D40: Phase 5 | E40: 45 days | F40: 2 | G40: 5500 | H40: 45 | I40: =F40*H40 -> 90 | J40: =I40*G40 -> 495000
B41: L25 | C41: Drainage gang (external sewer) | D41: Phase 5 | E41: 10 days | F41: 4 | G41: 4500 | H41: 10 | I41: =F41*H41 -> 40 | J41: =I41*G41 -> 180000
B42: L26 | C42: Water tank installation crew | D42: Phase 5 | E42: 3 days | F42: 3 | G42: 5000 | H42: 3 | I42: =F42*H42 -> 9 | J42: =I42*G42 -> 45000
B43: L27 | C43: Borehole casing & pump installation | D43: Phase 5 | E43: 5 days | F43: 3 | G43: 6000 | H43: 5 | I43: =F43*H43 -> 15 | J43: =I43*G43 -> 90000
B44: SUBTOTAL D — PLUMBING LABOUR | J44: =SUM(J39:J43) -> 1350000
B46: SECTION E — ELECTRICAL WORKS
B47: L28 | C47: Licensed electrician (master) | D47: Phase 5 | E47: 50 days | F47: 1 | G47: 15000 | H47: 50 | I47: =F47*H47 -> 50 | J47: =I47*G47 -> 750000
B48: L29 | C48: Electrician assistant | D48: Phase 5 | E48: 50 days | F48: 2 | G48: 6000 | H48: 50 | I48: =F48*H48 -> 100 | J48: =I48*G48 -> 600000
B49: L30 | C49: Solar system installer | D49: Phase 5 | E49: 5 days | F49: 2 | G49: 12000 | H49: 5 | I49: =F49*H49 -> 10 | J49: =I49*G49 -> 120000
B50: L31 | C50: EKEDC meter connection supervisor | D50: Phase 5 | E50: 2 days | F50: 1 | G50: 25000 | H50: 2 | I50: =F50*H50 -> 2 | J50: =I50*G50 -> 50000
B51: SUBTOTAL E — ELECTRICAL LABOUR | J51: =SUM(J47:J50) -> 1520000
B53: SECTION F — PLASTERING & SCREEDING
B54: L32 | C54: Master plasterer | D54: Phase 6 | E54: 45 days | F54: 2 | G54: 8500 | H54: 45 | I54: =F54*H54 -> 90 | J54: =I54*G54 -> 765000
B55: L33 | C55: Plasterer assistants | D55: Phase 6 | E55: 45 days | F55: 6 | G55: 4000 | H55: 45 | I55: =F55*H55 -> 270 | J55: =I55*G55 -> 1080000
B56: L34 | C56: Floor screeding gang | D56: Phase 6 | E56: 10 days | F56: 4 | G56: 5000 | H56: 10 | I56: =F56*H56 -> 40 | J56: =I56*G56 -> 200000
B57: L35 | C57: POP ceiling installer | D57: Phase 6 | E57: 15 days | F57: 3 | G57: 8000 | H57: 15 | I57: =F57*H57 -> 45 | J57: =I57*G57 -> 360000
B58: SUBTOTAL F — PLASTERING LABOUR | J58: =SUM(J54:J57) -> 2405000
B60: SECTION G — TILING
B61: L36 | C61: Master tiler (floor & wall) | D61: Phase 6 | E61: 40 days | F61: 2 | G61: 10000 | H61: 40 | I61: =F61*H61 -> 80 | J61: =I61*G61 -> 800000
B62: L37 | C62: Tiling assistants | D62: Phase 6 | E62: 40 days | F62: 4 | G62: 4500 | H62: 40 | I62: =F62*H62 -> 160 | J62: =I62*G62 -> 720000
B63: SUBTOTAL G — TILING LABOUR | J63: =SUM(J61:J62) -> 1520000
B65: SECTION H — PAINTING
B66: L38 | C66: Master painter | D66: Phase 6 | E66: 30 days | F66: 2 | G66: 8500 | H66: 30 | I66: =F66*H66 -> 60 | J66: =I66*G66 -> 510000
B67: L39 | C67: Painter assistants | D67: Phase 6 | E67: 30 days | F67: 4 | G67: 4000 | H67: 30 | I67: =F67*H67 -> 120 | J67: =I67*G67 -> 480000
B68: SUBTOTAL H — PAINTING LABOUR | J68: =SUM(J66:J67) -> 990000
B70: SECTION I — STEELWORK, DOORS & WINDOWS
B71: L40 | C71: Steel fabricator (staircase, railing) | D71: Phase 6 | E71: 15 days | F71: 2 | G71: 10000 | H71: 15 | I71: =F71*H71 -> 30 | J71: =I71*G71 -> 300000
B72: L41 | C72: Door & window fixing gang | D72: Phase 6 | E72: 10 days | F72: 4 | G72: 6000 | H72: 10 | I72: =F72*H72 -> 40 | J72: =I72*G72 -> 240000
B73: L42 | C73: Glass installation crew | D73: Phase 6 | E73: 5 days | F73: 3 | G73: 8000 | H73: 5 | I73: =F73*H73 -> 15 | J73: =I73*G73 -> 120000
B74: SUBTOTAL I — STEELWORK LABOUR | J74: =SUM(J71:J73) -> 660000
B76: SECTION J — EXTERNAL WORKS
B77: L43 | C77: Fence bricklayer & assistants | D77: Phase 6 | E77: 20 days | F77: 6 | G77: 5000 | H77: 20 | I77: =F77*H77 -> 120 | J77: =I77*G77 -> 600000
B78: L44 | C78: Gate fabricator & installer | D78: Phase 6 | E78: 5 days | F78: 3 | G78: 8000 | H78: 5 | I78: =F78*H78 -> 15 | J78: =I78*G78 -> 120000
B79: L45 | C79: Paving block layer | D79: Phase 6 | E79: 15 days | F79: 4 | G79: 5500 | H79: 15 | I79: =F79*H79 -> 60 | J79: =I79*G79 -> 330000
B80: L46 | C80: General labourer (site cleaning, misc.) | D80: Phase 1–6 | E80: 180 days | F80: 2 | G80: 3500 | H80: 180 | I80: =F80*H80 -> 360 | J80: =I80*G80 -> 1260000
B81: L47 | C81: Security watchman (site) | D81: Phase 1–6 | E81: 540 days | F81: 1 | G81: 2500 | H81: 540 | I81: =F81*H81 -> 540 | J81: =I81*G81 -> 1350000
B82: SUBTOTAL J — EXTERNAL WORKS LABOUR | J82: =SUM(J77:J81) -> 3660000
B85: GRAND TOTAL LABOUR COST | J85: =SUM(J7:J83) -> 49765000

Sheet Supplier Analysis
B1: SUPPLIER EVALUATION & SELECTION ANALYSIS
B2: Weighted scoring methodology — All suppliers evaluated on 5 criteria (1–10 scale)
B4: EVALUATION CRITERIA WEIGHTS
C5: Criteria | D5: Weight
B6: C1 | C6: Price Competitiveness | D6: 30% | E6: How competitive is the quoted price vs market?
B7: C2 | C7: Delivery Lead Time | D7: 20% | E7: Can they supply on schedule — critical for construction timeline?
B8: C3 | C8: Product Quality / Standard | D8: 25% | E8: Do they meet SON, NAFDAC, or project specifications?
B9: C4 | C9: Financial Stability & Track Record | D9: 15% | E9: Are they registered, with references and financial capacity?
B10: C5 | C10: After-Sales / Warranty Support | D10: 10% | E10: Do they offer replacement, warranty, or post-supply support?
B12: SUPPLIER SCORECARD — KEY MATERIAL CATEGORIES
B13: CATEGORY 1: CEMENT (Dangote, Lafarge, BUA)
B14: Supplier | C14: Location | D14: Price | E14: Lead Time | F14: Quality | G14: Track Record | H14: Warranty | I14: Wtd Score | J14: Decision
B15: Dangote Cement Dist. | C15: Ilupeju, Lagos | D15: 9 | E15: 8 | F15: 9 | G15: 8 | H15: 7 | I15: 8.45 | J15: ✓ SELECTED
B16: Lafarge Nigeria | C16: Ikeja, Lagos | D16: 8 | E16: 9 | F16: 9 | G16: 7 | H16: 8 | I16: 8.3 | J16: Not selected
B17: BUA Cement Dealer | C17: Mushin, Lagos | D17: 8 | E17: 7 | F17: 8 | G17: 8 | H17: 6 | I17: 7.6 | J17: Not selected
B18: RATIONALE: Highest weighted score (8.55). Best price competitiveness and quality consistency. Framework agreement for 650 bags secured at ₦7,200/bag.
B20: CATEGORY 2: STEEL RODS (Dangote Steel, Delta Steel)
B21: Supplier | C21: Location | D21: Price | E21: Lead Time | F21: Quality | G21: Track Record | H21: Warranty | I21: Wtd Score | J21: Decision
B22: Dangote Steel | C22: Apapa, Lagos | D22: 9 | E22: 8 | F22: 9 | G22: 9 | H22: 7 | I22: 8.6 | J22: ✓ SELECTED
B23: Delta Steel Products | C23: Surulere, Lagos | D23: 8 | E23: 8 | F23: 8 | G23: 7 | H23: 7 | I23: 7.75 | J23: Not selected
B24: BIS Steel Nigeria | C24: Oshodi, Lagos | D24: 8 | E24: 7 | F24: 8 | G24: 7 | H24: 6 | I24: 7.45 | J24: Not selected
B25: RATIONALE: Best price and SON-certified quality. Consistent grade Y8–Y25 available. Volume discount secured for 7.3 tonnes total.
B27: CATEGORY 3: BLOCKS (Premier Blocks Ltd)
B28: Supplier | C28: Location | D28: Price | E28: Lead Time | F28: Quality | G28: Track Record | H28: Warranty | I28: Wtd Score | J28: Decision
B29: Premier Blocks Ltd | C29: Ojodu, Lagos | D29: 9 | E29: 9 | F29: 9 | G29: 8 | H29: 8 | I29: 8.75 | J29: ✓ SELECTED
B30: Strongblock Nigeria | C30: Ipaja, Lagos | D30: 8 | E30: 8 | F30: 8 | G30: 7 | H30: 7 | I30: 7.75 | J30: Not selected
B31: Afrimass Blocks | C31: Agege, Lagos | D31: 7 | E31: 8 | F31: 7 | G31: 7 | H31: 6 | I31: 7.1 | J31: Not selected
B32: RATIONALE: Premium score (8.80). Delivers to site. Consistent 9" and 6" sizes meeting NIS 87. Best warranty on replacement of defective units.
B34: CATEGORY 4: ROOFING (Alum Roofing Ng)
B35: Supplier | C35: Location | D35: Price | E35: Lead Time | F35: Quality | G35: Track Record | H35: Warranty | I35: Wtd Score | J35: Decision
B36: Alum Roofing Ng | C36: Ikeja, Lagos | D36: 9 | E36: 8 | F36: 8 | G36: 8 | H36: 8 | I36: 8.3 | J36: ✓ SELECTED
B37: Bond Aluminium | C37: Isolo, Lagos | D37: 8 | E37: 8 | F37: 8 | G37: 7 | H37: 7 | I37: 7.75 | J37: Not selected
B38: MetroRoof Nigeria | C38: Agbara, Ogun | D38: 7 | E38: 7 | F38: 8 | G38: 7 | H38: 6 | I38: 7.15 | J38: Not selected
B39: RATIONALE: Best price per sqm at ₦3,800. Delivers factory-direct. 1-year warranty on material defects. 0.55mm gauge confirmed.
B41: CATEGORY 5: TILES (Eleganza)
B42: Supplier | C42: Location | D42: Price | E42: Lead Time | F42: Quality | G42: Track Record | H42: Warranty | I42: Wtd Score | J42: Decision
B43: Eleganza Tiles | C43: Ojodu, Lagos | D43: 8 | E43: 9 | F43: 9 | G43: 8 | H43: 9 | I43: 8.55 | J43: ✓ SELECTED
B44: Porcelain Palace Ng | C44: Victoria Island | D44: 7 | E44: 8 | F44: 9 | G44: 8 | H44: 8 | I44: 7.95 | J44: Not selected
B45: Marshalls Tiles Nigeria | C45: Lekki | D45: 7 | E45: 7 | F45: 8 | G45: 8 | H45: 7 | I45: 7.4 | J45: Not selected
B46: RATIONALE: Highest overall score (8.70). Consistent stock availability, ISO quality, and competitive pricing. Replacement guarantee for breakages.
B48: CATEGORY 6: ELECTRICAL CABLES (Nigerchin)
B49: Supplier | C49: Location | D49: Price | E49: Lead Time | F49: Quality | G49: Track Record | H49: Warranty | I49: Wtd Score | J49: Decision
B50: Nigerchin Cables | C50: Ikeja, Lagos | D50: 9 | E50: 8 | F50: 9 | G50: 8 | H50: 8 | I50: 8.55 | J50: ✓ SELECTED
B51: Coleman Cables Nig. | C51: Lekki, Lagos | D51: 8 | E51: 8 | F51: 9 | G51: 8 | H51: 7 | I51: 8.15 | J51: Not selected
B52: PZ Cables Nigeria | C52: Apapa, Lagos | D52: 8 | E52: 7 | F52: 8 | G52: 7 | H52: 6 | I52: 7.45 | J52: Not selected
B53: RATIONALE: SON-certified. Best price for 2.5mm and 4mm cables. Full stock availability. Technical support on wiring schedule provided.
B55: CATEGORY 7: PLUMBING (Vanguard Pipes)
B56: Supplier | C56: Location | D56: Price | E56: Lead Time | F56: Quality | G56: Track Record | H56: Warranty | I56: Wtd Score | J56: Decision
B57: Vanguard Pipes | C57: Mushin, Lagos | D57: 9 | E57: 9 | F57: 8 | G57: 8 | H57: 8 | I57: 8.5 | J57: ✓ SELECTED
B58: Aquatech Pipes Nig. | C58: Ikeja, Lagos | D58: 8 | E58: 8 | F58: 8 | G58: 8 | H58: 7 | I58: 7.9 | J58: Not selected
B59: Georg Fischer Nig. | C59: V/Island, Lagos | D59: 7 | E59: 7 | F59: 9 | G59: 9 | H59: 9 | I59: 8 | J59: Not selected
B60: RATIONALE: Best price and fastest delivery. uPVC and PPR pipes in all required sizes available in Lagos stock. 3-year fitting warranty.
B62: CATEGORY 8: READY MIX CONCRETE (Lafarge ReadyMix)
B63: Supplier | C63: Location | D63: Price | E63: Lead Time | F63: Quality | G63: Track Record | H63: Warranty | I63: Wtd Score | J63: Decision
B64: Lafarge ReadyMix | C64: Sagamu Rd, Lagos | D64: 8 | E64: 9 | F64: 9 | G64: 9 | H64: 8 | I64: 8.6 | J64: ✓ SELECTED
B65: Readymix Concrete Ng | C65: Oshodi, Lagos | D65: 8 | E65: 8 | F65: 8 | G65: 8 | H65: 7 | I65: 7.9 | J65: Not selected
B66: Dantata & Sawoe | C66: Ikeja, Lagos | D66: 7 | E66: 7 | F66: 8 | G66: 8 | H66: 7 | I66: 7.4 | J66: Not selected
B67: RATIONALE: Best quality assurance. 25N/mm² guaranteed with test cubes. 8-hour SLA on delivery. Most reliable for foundation pour scheduling.

Sheet Professional Fees
B1: PROFESSIONAL FEES & CONSULTANCY COSTS
B2: Regulatory, consultancy, and statutory costs in Nigerian Naira (₦)
B4: TOTAL PROFESSIONAL FEES | G4: =F22 -> 5065000
B6: # | C6: Service Description | D6: Service Provider | E6: Basis | F6: Amount (₦) | G6: Notes
B7: PF-01 | C7: Architectural Design & Drawings | D7: Arch. Biodun Adeleke (ARCON Registered) | E7: % of contract | F7: 850000 | G7: Full working drawings, 3D visualization, and specification
B8: PF-02 | C8: Structural Engineering Design | D8: Engr. Chike Okonkwo (COREN Registered) | E8: Lump sum | F8: 650000 | G8: Structural calculations, foundation design, raft slab specification
B9: PF-03 | C9: Quantity Surveying Services | D9: QS Tunde Adesola (NIQS Member) | E9: % of contract | F9: 480000 | G9: BOQ preparation, cost planning, valuation, and final account
B10: PF-04 | C10: Building Plan Approval (LASBCA) | D10: Lagos State Building Control Agency | E10: Statutory fee | F10: 380000 | G10: Approval of building plans per Lagos State Urban Planning Law
B11: PF-05 | C11: Environmental Impact Assessment | D11: Lagos State EPA | E11: Statutory fee | F11: 120000 | G11: EIA report for development in designated zone
B12: PF-06 | C12: Survey & Deed of Assignment | D12: Licensed surveyor — Surveyor Musa Bello | E12: Lump sum | F12: 250000 | G12: Certificate of Occupancy (C of O) processing and survey plan
B13: PF-07 | C13: Project Management Supervision | D13: PM Consultant — Construct-Pro Ltd | E13: Monthly retainer × 18 | F13: 720000 | G13: Monthly site visits, progress reports, contractor management
B14: PF-08 | C14: Soil Investigation / Geotechnical Report | D14: GeoTech Nigeria Ltd | E14: Lump sum | F14: 180000 | G14: Borehole logs, bearing capacity, German floor specification
B15: PF-09 | C15: MEP Engineering (M&E Design) | D15: MEP Consultants Nigeria | E15: Lump sum | F15: 320000 | G15: Mechanical, electrical and plumbing design and specifications
B16: PF-10 | C16: Insurance — Contractor All Risk (CAR) | D16: AXA Mansard Insurance | E16: Annual premium | F16: 285000 | G16: 18-month CAR policy covering materials, plant, and third-party liability
B17: PF-11 | C17: Water Board Connection Approval | D17: Lagos Water Corporation | E17: Statutory fee | F17: 85000 | G17: Water mains connection application and approval
B18: PF-12 | C18: EKEDC Electrical Connection | D18: Eko Electricity Distribution Co. | E18: Statutory fee | F18: 125000 | G18: Meter and service connection to national grid
... B21: PF-15 | C21: Procurement Officer Professional Fee | D21: Self (Portfolio Owner) | E21: Lump sum | F21: 450000 | G21: Full procurement management — 18 months: sourcing, tendering, contracting
B22: TOTAL PROFESSIONAL FEES | F22: =SUM(F7:F21) -> 5065000

Sheet PO Tracker
B1: PROCUREMENT SCHEDULE & PURCHASE ORDER TRACKER
B2: Live tracking of all material procurement orders | 3-Bedroom Flat Project | 2025
B4: PO No. | C4: Material/Service | D4: Supplier | E4: Phase | F4: Qty | G4: PO Value (₦) | H4: Order Date | I4: Expected Delivery | J4: Actual Delivery | K4: Status | L4: Payment Status
B5: PO-001 | C5: Geotechnical/Soil Investigation | D5: GeoTech Nigeria Ltd | E5: Pre-Construction | F5: 1 lot | G5: 180000 | H5: 05-Jan-2025 | I5: 15-Jan-2025 | J5: 15-Jan-2025 | K5: DELIVERED | L5: PAID
B6: PO-002 | C6: Architectural & Structural Drawings | D6: Arch. Adeleke & Engr. Okonkwo | E6: Pre-Construction | F6: 1 lot | G6: 1500000 | H6: 05-Jan-2025 | I6: 28-Feb-2025 | J6: 28-Feb-2025 | K6: DELIVERED | L6: PAID
B7: PO-003 | C7: LASBCA Building Plan Approval | D7: Lagos State Building Control | E7: Pre-Construction | F7: 1 lot | G7: 380000 | H7: 10-Jan-2025 | I7: 15-Mar-2025 | J7: 15-Mar-2025 | K7: DELIVERED | L7: PAID
B8: PO-004 | C8: Site Clearing & Excavation | D8: Kola Excavators | E8: Phase 1 | F8: 1 | G8: 756000 | H8: 20-Mar-2025 | I8: 25-Mar-2025 | J8: 24-Mar-2025 | K8: DELIVERED | L8: PAID
B9: PO-005 | C9: Anti-Termite Treatment | D9: Termiguard Nig. | E9: Phase 1 | F9: 180 | G9: 216000 | H9: 22-Mar-2025 | I9: 23-Mar-2025 | J9: 23-Mar-2025 | K9: DELIVERED | L9: PAID
B10: PO-006 | C10: Hardcore Supply & Compaction | D10: Suntech Nig. Ltd | E10: Phase 1 | F10: 1 | G10: 461500 | H10: 23-Mar-2025 | I10: 25-Mar-2025 | J10: 25-Mar-2025 | K10: DELIVERED | L10: PAID
B11: PO-007 | C11: BRC Mesh A393 (30 sheets) | D11: Steel Baron Nig. | E11: Phase 1 | F11: 30 | G11: 2550000 | H11: 25-Mar-2025 | I11: 30-Mar-2025 | J11: 30-Mar-2025 | K11: DELIVERED | L11: PAID
B12: PO-008 | C12: Dangote Cement — Batch 1 (200 bags) | D12: Dangote Cement Dist. | E12: Phase 1 | F12: 200 | G12: 1440000 | H12: 26-Mar-2025 | I12: 28-Mar-2025 | J12: 28-Mar-2025 | K12: DELIVERED | L12: PAID
B13: PO-009 | C13: Granite & Sharp Sand — Batch 1 | D13: Apapa Quarry Ltd / Lagos Sand | E13: Phase 1 | F13: 1 | G13: 1650000 | H13: 27-Mar-2025 | I13: 29-Mar-2025 | J13: 29-Mar-2025 | K13: DELIVERED | L13: PAID
B14: PO-010 | C14: Ready Mix Concrete — Raft Slab | D14: Lafarge ReadyMix | E14: Phase 1 | F14: 47 | G14: 2580000 | H14: 01-Apr-2025 | I14: 03-Apr-2025 | J14: 03-Apr-2025 | K14: DELIVERED | L14: PAID
B15: PO-011 | C15: Mild Steel Rods Y16 & Y12 (Foundation) | D15: Dangote Steel | E15: Phase 1 | F15: 1.3 | G15: 845000 | H15: 28-Mar-2025 | I15: 31-Mar-2025 | J15: 31-Mar-2025 | K15: DELIVERED | L15: PAID
B16: PO-012 | C16: DPC Bricks & Damp Proof Membrane | D16: Premier Blocks Ltd / BuildPro | E16: Phase 1 | F16: 1 | G16: 478000 | H16: 01-Apr-2025 | I16: 03-Apr-2025 | J16: 05-Apr-2025 | K16: DELIVERED | L16: PAID
B17: PO-013 | C17: 9-inch Hollow Blocks (4200 units) | D17: Premier Blocks Ltd | E17: Phase 2 | F17: 4200 | G17: 1596000 | H17: 15-Apr-2025 | I17: 20-Apr-2025 | J17: 22-Apr-2025 | K17: DELIVERED | L17: PAID
B18: PO-014 | C18: 6-inch Solid Blocks (3500 units) | D18: Premier Blocks Ltd | E18: Phase 2 | F18: 3500 | G18: 1120000 | H18: 15-Apr-2025 | I18: 20-Apr-2025 | J18: 21-Apr-2025 | K18: DELIVERED | L18: PAID
B19: PO-015 | C19: Dangote Cement — Batch 2 (300 bags) | D19: Dangote Cement Dist. | E19: Phase 2 | F19: 300 | G19: 2160000 | H19: 20-Apr-2025 | I19: 22-Apr-2025 | J19: 23-Apr-2025 | K19: DELIVERED | L19: PAID
... B30: PO-026 | C30: All Plumbing Materials (uPVC, PPR, fittings) | D30: Vanguard Pipes | E30: Phase 5 | F30: 1 | G30: 2714000 | H30: 01-Sep-2025 | I30: 10-Sep-2025 | J30: 11-Sep-2025 | K30: DELIVERED | L30: PARTIAL PMT
B31: PO-027 | C31: Bathroom Fittings (WC, basins, showers) | D31: Sanitech Nig. | E31: Phase 5 | F31: 1 | G31: 645000 | H31: 01-Sep-2025 | I31: 10-Sep-2025 | K31: ON ORDER | L31: DEPOSIT PAID
B32: PO-028 | C32: Electrical Cables (all gauges) | D32: Nigerchin Cables | E32: Phase 5 | F32: 1 | G32: 1086000 | H32: 01-Sep-2025 | I32: 08-Sep-2025 | J32: 08-Sep-2025 | K32: DELIVERED | L32: PAID
B33: PO-029 | C33: Distribution Board, MCBs & Sockets | D33: Clipsal Nigeria / Schneider | E33: Phase 5 | F33: 1 | G33: 428200 | H33: 05-Sep-2025 | I33: 10-Sep-2025 | K33: AWAITING | L33: NOT PAID
B34: PO-030 | C34: Inverter, Batteries & Solar Panels | D34: Victron Energy / Jinko Solar | E34: Phase 5 | F34: 1 | G34: 1472000 | H34: 05-Sep-2025 | I34: 20-Sep-2025 | K34: ON ORDER | L34: DEPOSIT PAID
B35: PO-031 | C35: Aluminium Windows (all types) | D35: Alumaco Nig. Ltd | E35: Phase 5 | F35: 20 | G35: 1542000 | H35: 10-Sep-2025 | I35: 25-Sep-2025 | K35: ON ORDER | L35: DEPOSIT PAID
B36: PO-032 | C36: Security Doors (main & back) | D36: Ironmax Nig. | E36: Phase 5 | F36: 2 | G36: 660000 | H36: 10-Sep-2025 | I36: 20-Sep-2025 | K36: ON ORDER | L36: NOT PAID
B37: PO-033 | C37: Internal & Bathroom Doors | D37: Woodcraft Nig. | E37: Phase 6 | F37: 12 | G37: 742200 | H37: 15-Oct-2025 | I37: 01-Nov-2025 | K37: PENDING | L37: NOT PAID
B38: PO-034 | C38: All Floor & Wall Tiles | D38: Eleganza Tiles | E38: Phase 6 | F38: 1 | G38: 3876500 | H38: 01-Nov-2025 | I38: 15-Nov-2025 | K38: PENDING | L38: NOT PAID
B39: PO-035 | C39: Tile Adhesive & Grout | D39: Weber Nigeria | E39: Phase 6 | F39: 1 | G39: 534000 | H39: 01-Nov-2025 | I39: 10-Nov-2025 | K39: PENDING | L39: NOT PAID
B40: PO-036 | C40: Paints (Dulux Interior & Exterior) | D40: Dulux Nigeria | E40: Phase 6 | F40: 1 | G40: 1562000 | H40: 15-Nov-2025 | I40: 25-Nov-2025 | K40: PENDING | L40: NOT PAID
B41: PO-037 | C41: POP Ceiling Boards & Cornices | D41: CeilPro Nig. | E41: Phase 6 | F41: 1 | G41: 1623000 | H41: 15-Nov-2025 | I41: 30-Nov-2025 | K41: PENDING | L41: NOT PAID
B42: PO-038 | C42: Staircase Steel & Handrails | D42: SteelFab Nig. | E42: Phase 6 | F42: 1 | G42: 1391000 | H42: 01-Dec-2025 | I42: 20-Dec-2025 | K42: PENDING | L42: NOT PAID
B43: PO-039 | C43: Gate, Fence Blocks & Driveway Paving | D43: Ironmax / Premier / Interloc Nig. | E43: Phase 6 | F43: 1 | G43: 3659000 | H43: 01-Jan-2026 | I43: 28-Feb-2026 | K43: PENDING | L43: NOT PAID
B44: PO-040 | C44: Borehole Drilling & Water System | D44: Aqua Drill Nig. | E44: Phase 6 | F44: 1 | G44: 1200000 | H44: 15-Jan-2026 | I44: 01-Mar-2026 | K44: PENDING | L44: NOT PAID
B45: TOTAL COMMITTED PROCUREMENT VALUE | G45: =SUM(G5:G44) -> 52924900
B47: TOTAL POs ISSUED | E47: DELIVERED | H47: ON ORDER / PENDING | K47: PAID
B48: =COUNTA(B5:B44) -> 40 | E48: =COUNTIF(K5:K44,"DELIVERED") -> 27 | H48: =COUNTIF(K5:K44,"ON ORDER")+COUNTIF(K5:K44,"PENDING") -> 12 | K48: =COUNTIF(L5:L44,"PAID") -> 26

Sheet Budget Summary
B1: PROJECT BUDGET SUMMARY & COST ANALYSIS
B2: 3-Bedroom Flat | German Floor Foundation | Lagos, Nigeria | All figures in ₦
B4: MATERIALS COST | C4: LABOUR COST | D4: PROFESSIONAL FEES | E4: CONTINGENCY (10%) | F4: GRAND TOTAL
B5: ='Bill of Quantities'!L175 -> 63574700 | C5: ='Labour Cost'!J4 -> 49765000 | D5: ='Professional Fees'!F4 -> 0 | E5: =('Bill of Quantities'!L175+'Labour Cost'!J4+'Professional Fees'!F4)*0.1 -> 11333970 | F5: ='Bill of Quantities'!L175+'Labour Cost'!J4+'Professional Fees'!F4+('Bill of Quantities'!L175+'Labour Cost'!J4+'Professional Fees'!F4)*0.1 -> 124673670
B6: ₦ | C6: ₦ | D6: ₦ | E6: ₦ | F6: ₦
B8: BUDGET BREAKDOWN BY CONSTRUCTION PHASE
B9: Phase | C9: Description | D9: Materials (₦) | E9: Labour (₦) | F9: Total (₦) | G9: % of Budget
B10: Phase 1 | C10: Site Preparation & German Floor Foundation | D10: 3392000 | E10: 825000 | F10: =D10+E10 -> 4217000 | G10: =F10/SUM(F10:F15) -> 0.092949545
B11: Phase 2 | C11: Ground Floor Superstructure (Block, Concrete, Steel) | D11: 7255000 | E11: 1980000 | F11: =D11+E11 -> 9235000 | G11: =F11/SUM(F10:F15) -> 0.20355443
B12: Phase 3 | C12: First Floor Superstructure | D12: 5620000 | E12: 1820000 | F12: =D12+E12 -> 7440000 | G12: =F12/SUM(F10:F15) -> 0.16398971
B13: Phase 4 | C13: Roofing Works | D13: 3491500 | E13: 760000 | F13: =D13+E13 -> 4251500 | G13: =F13/SUM(F10:F15) -> 0.093709981
B14: Phase 5 | C14: MEP (Plumbing, Electrical, Solar) | D14: 6345200 | E14: 1380000 | F14: =D14+E14 -> 7725200 | G14: =F14/SUM(F10:F15) -> 0.17027598
B15: Phase 6 | C15: Finishing (Tiling, Painting, Doors, Fencing) | D15: 9850000 | E15: 2650000 | F15: =D15+E15 -> 12500000 | G15: =F15/SUM(F10:F15) -> 0.27552035
B16: TOTAL (excl. Fees & Contingency) | D16: =SUM(D10:D15) -> 35953700 | E16: =SUM(E10:E15) -> 9415000 | F16: =SUM(F10:F15) -> 45368700
B18: PROCUREMENT STRATEGY HIGHLIGHTS
B19: Competitive Tendering | C19: All major materials (cement, steel, concrete, tiles) subjected to minimum 3-quote process. Lowest compliant bid selected. | F19: ₦ Savings: ~₦4.2M (vs. highest quotes)
B20: Framework Agreements | C20: Cement (650 bags @ ₦7,200), Blocks (10,500 units), Steel (7.3 tonnes) — locked-in unit rates with approved suppliers. | F20: Risk mitigation: Price inflation protection
B21: Staged Procurement | C21: Materials procured phase-by-phase to avoid over-stocking, reduce storage risk, and optimize cash flow. | F21: Cash flow: Avoids ₦15M+ upfront capital tie-up
B22: Local Sourcing Priority | C22: 70% of materials sourced within 30km of site (Lagos metropolis). Reduces transport cost & lead time significantly. | F22: Logistics savings: ~₦850,000 estimated
B23: Vendor Pre-Qualification | C23: All vendors verified: CAC registration, SON certification, bank statements, and site visit references required. | F23: Quality assurance: Zero non-conforming deliveries to date
B24: PO Documentation | C24: 100% of purchases covered by formal Purchase Orders with delivery terms, inspection, and payment milestones. | F24: Compliance: Full audit trail for all transactions
